pylya/__init__.py
pylya/source/__init__.py
pylya/source/analysis.py
pylya/source/meta.py
pylya/source/tools.py
pylya-0.0.8.dist-info/METADATA
pylya-0.0.8.dist-info/WHEEL
pylya-0.0.8.dist-info/top_level.txt
pylya-0.0.8.dist-info/RECORD
