Metadata-Version: 2.1
Name: pylya
Version: 0.0.8
Summary: Coarse-grained Dynamic Analysis for Python
Author: Konstantinos Filopoulos
